{
  "id": "10466945",
  "url": "https://www.autoscout24.ch/de/hci/v2/1124/detail/10466945",
  "scraped_at": "2025-08-14T15:18:54.842Z",
  "dealer": "Auto Voegeli AG",
  "title": "SWM HOKU 125 ABS",
  "price": "CHF 3&#x27;990.-",
  "priceNumber": 3,
  "month": "14",
  "year": "1217",
  "date": "14.1217",
  "mileage": "25 km",
  "mileageNumber": 25,
  "type": "Naked bike",
  "transmission": "Schaltgetriebe manuell",
  "fuel": "Benzin",
  "drive": "Kette",
  "power": "11 kW",
  "displacement": null,
  "consumption": "-",
  "co2Emission": 2,
  "phones": [
    "032 652 11 66",
    "078 636 06 19"
  ],
  "primaryPhone": "032 652 11 66",
  "whatsappPhone": "078 636 06 19",
  "businessPhone": "032 652 11 66",
  "location": "Solothurnstrasse 129, 2540 Grenchen",
  "equipment": [
    "Neu bereift"
  ],
  "mfk": "Ja",
  "warranty": "Ja",
  "warrantyDetails": "!",
  "warrantyMonths": 24,
  "warrantyType": "from-first-registration",
  "occGarantie": false,
  "fahrzeugbeschreibung": "Hochwertiges Fahrzeug von Auto Vögeli AG",
  "brand": "SWM",
  "model": "HOKU 125 ABS",
  "condition": "Gebraucht",
  "images": [
    "https://images.autoscout24.ch/public/listing/945/10466945/1.jpg",
    "https://images.autoscout24.ch/public/listing/945/10466945/2.jpg",
    "https://images.autoscout24.ch/public/listing/945/10466945/4.jpg",
    "https://images.autoscout24.ch/public/listing/945/10466945/5.jpg",
    "https://images.autoscout24.ch/public/listing/945/10466945/6.jpg",
    "https://images.autoscout24.ch/public/listing/945/10466945/7.jpg",
    "https://images.autoscout24.ch/public/listing/945/10466945/0.jpg"
  ],
  "imageCount": 7
}