{
  "id": "11452796",
  "url": "https://www.autoscout24.ch/de/hci/v2/1124/detail/11452796",
  "scraped_at": "2025-08-14T15:18:04.091Z",
  "dealer": "Auto Voegeli AG",
  "title": "VOGE 900 DSX Adventure",
  "price": "CHF 9&#x27;790.-",
  "priceNumber": 9,
  "month": "14",
  "year": "1217",
  "date": "14.1217",
  "mileage": "50 km",
  "mileageNumber": 50,
  "type": "chopper",
  "transmission": "Stufenlos",
  "fuel": "Benzin",
  "drive": "Kette",
  "power": "70 kW",
  "displacement": null,
  "consumption": "-",
  "co2Emission": 2,
  "phones": [
    "032 652 11 66",
    "078 636 06 19"
  ],
  "primaryPhone": "032 652 11 66",
  "whatsappPhone": "078 636 06 19",
  "businessPhone": "032 652 11 66",
  "location": "Solothurnstrasse 129, 2540 Grenchen",
  "equipment": [
    "Windschutzscheibe",
    "Bluetooth-Schnittstelle",
    "Aluminiumfelgen",
    "Doppelscheibenbremse",
    "Adaptiver Tempomat",
    "Schutzbügel",
    "Beheizbare Griffe",
    "LED-Scheinwerfer",
    "Navigation",
    "Speichenräder"
  ],
  "mfk": "Ja",
  "warranty": "Ja",
  "warrantyDetails": "!",
  "warrantyMonths": 36,
  "warrantyType": "from-first-registration",
  "occGarantie": false,
  "fahrzeugbeschreibung": "🏍️ MOTORRÄDER LAGEAUSVERKAUF – ZUGREIFEN, BEVOR ALLES WEG IST! 🏁\\n\\nViele unserer Top-Bikes sind bereits verkauft – aber Nachschub ist unterwegs!\\n🔜 Bald wieder verfügbar – sichere dir jetzt dein Traumbike zum Sonderpreis!\\nVOGE 900 DSX ABS ADVENTURE\\nin 3 Farben erhältlich Neu Fahrzeug mit 3 Jahre Hersteller-Garantie,Neufahrzeug das wir an Lager haben, sofort verfügbar!<br><br>* Verkaufspreis inkl. 8,1% MwSt exkl. Nebenkosten.\\n\\n- Tempomat\\n- Toten Winkel Assistent\\n- KYB-Fahrwerk\\n- Brembo Bremsanlage\\n- LED-Scheinwerfer\\n- Nebelscheinwerfer\\n- Quickshifter\\n- Griff und Sitzheizung\\n- Infotaiment-System\\n- 3 Fahrmodi\\n\\nKOFFERSET ist OPTIONAL erhältlich",
  "brand": "VOGE",
  "model": "900 DSX Adventure",
  "condition": "Gebraucht",
  "images": [
    "https://images.autoscout24.ch/public/listing/796/11452796/776997972.jpg",
    "https://images.autoscout24.ch/public/listing/796/11452796/2127131301.jpg",
    "https://images.autoscout24.ch/public/listing/796/11452796/2113832209.jpg",
    "https://images.autoscout24.ch/public/listing/796/11452796/1029542041.jpg",
    "https://images.autoscout24.ch/public/listing/796/11452796/931090393.jpg",
    "https://images.autoscout24.ch/public/listing/796/11452796/292714238.jpg",
    "https://images.autoscout24.ch/public/listing/796/11452796/1709537677.jpg",
    "https://images.autoscout24.ch/public/listing/796/11452796/1747747948.jpg",
    "https://images.autoscout24.ch/public/listing/796/11452796/84528597.jpg",
    "https://images.autoscout24.ch/public/listing/796/11452796/1008266669.jpg",
    "https://images.autoscout24.ch/public/listing/796/11452796/2053535581.jpg",
    "https://images.autoscout24.ch/public/listing/796/11452796/801235125.jpg",
    "https://images.autoscout24.ch/public/listing/796/11452796/841999024.jpg",
    "https://images.autoscout24.ch/public/listing/796/11452796/280031129.jpg",
    "https://images.autoscout24.ch/public/listing/796/11452796/1161786155.jpg",
    "https://images.autoscout24.ch/public/listing/796/11452796/1220606771.jpg"
  ],
  "imageCount": 16
}